CHANGES.txt
MANIFEST.in
README.md
setup.py
scripts/learn
scseg/__init__.py
scseg/core.py
scseg/digital.py
scseg/learn.py
scseg/quantifier.py
scseg/word.py
scseg.egg-info/PKG-INFO
scseg.egg-info/SOURCES.txt
scseg.egg-info/dependency_links.txt
scseg.egg-info/not-zip-safe
scseg.egg-info/requires.txt
scseg.egg-info/top_level.txt
scseg/data/admin.dic
scseg/data/brand.dic
scseg/data/chars.dic
scseg/data/internet.dic
scseg/data/nation.dic
scseg/data/people.dic
scseg/data/quantifier.unit
scseg/data/readme.txt
scseg/data/short_admin.dic
scseg/data/short_nation.dic
scseg/data/unit.dic
scseg/data/words.dic
scseg/route/__init__.py
scseg/route/mmseg.py