Metadata-Version: 1.0
Name: scseg
Version: 1.7.4
Summary: a python chinese seg word
Home-page: https://github.com/duanhongyi/scseg
Author: duanhongyi
Author-email: duanhyi@gmail.com
License: BSD
Keywords: Chinese Word Segmentation 中文 分词 工具包 汉语
Platform: all platform
Classifier: Programming Language :: Python
